<?xml version="1.1" encoding="UTF-8" standalone="no"?>
<databaseChangeLog xmlns:xsi="http://www.w3.org/2001/XMLSchema-instance"
                   xmlns="http://www.liquibase.org/xml/ns/dbchangelog"
                   xsi:schemaLocation="http://www.liquibase.org/xml/ns/dbchangelog http://www.liquibase.org/xml/ns/dbchangelog/dbchangelog-3.6.xsd">

    <changeSet author="saeb (generated)" id="1596267426191-233">
        <createSequence sequenceName="SEQ_BILL_OF_LANDING"/>
    </changeSet>
    <changeSet author="saeb (generated)" id="1596267426191-236">
        <createTable tableName="TBL_CNTR_BILL_OF_LANDING">
            <column autoIncrement="true" name="id" type="NUMBER(19, 0)">
                <constraints primaryKey="true" primaryKeyName="TBL_CNTR_BILL_OF_LANDINGPK"/>
            </column>
            <column name="c_created_by" type="VARCHAR2(255 CHAR)">
                <constraints nullable="false"/>
            </column>
            <column name="d_created_date" type="TIMESTAMP">
                <constraints nullable="false"/>
            </column>
            <column name="c_last_modified_by" type="VARCHAR2(255 CHAR)"/>
            <column name="d_last_modified_date" type="TIMESTAMP"/>
            <column name="n_version" type="NUMBER(10, 0)">
                <constraints nullable="false"/>
            </column>
            <column defaultValueNumeric="1" name="N_E_STATUS" type="NUMBER">
                <constraints nullable="false"/>
            </column>
            <column defaultValueNumeric="1" name="B_EDITABLE" type="NUMBER">
                <constraints nullable="false"/>
            </column>
            <column name="F_CONTACT_CONSIGNEE_EXPORTER" type="NUMBER(19, 0)">
                <constraints nullable="false"/>
            </column>
            <column name="D_DATE_OF_ISSUE" type="TIMESTAMP"/>
            <column name="C_DESCRIPTION" type="VARCHAR2(4000 CHAR)"/>
            <column name="C_DESCRIPTION_CONTAINER" type="VARCHAR2(4000 CHAR)"/>
            <column name="C_DESCRIPTION_REMITTANCE" type="VARCHAR2(4000 CHAR)"/>
            <column name="C_DOCUMENT_NO" type="VARCHAR2(255 CHAR)">
                <constraints nullable="false"/>
            </column>
            <column name="F_CONTACT_NOTIFY_PARTY" type="NUMBER(19, 0)">
                <constraints nullable="false"/>
            </column>
            <column name="N_COPY_NUMBER_OF_BL" type="NUMBER(10, 0)"/>
            <column name="F_VESSEL" type="NUMBER(19, 0)"/>
            <column name="C_PLACE_OF_DELIVERY" type="VARCHAR2(255 CHAR)">
                <constraints nullable="false"/>
            </column>
            <column name="C_PLACE_OF_ISSUE" type="VARCHAR2(255 CHAR)"/>
            <column name="F_PORT_AS_DISCHARGE" type="NUMBER(19, 0)">
                <constraints nullable="false"/>
            </column>
            <column name="F_PORT_AS_LOADING" type="NUMBER(19, 0)">
                <constraints nullable="false"/>
            </column>
            <column name="F_CONTACT_SHIPPER_EXPORTER" type="NUMBER(19, 0)">
                <constraints nullable="false"/>
            </column>
            <column name="F_CONTACT_SWITCH_CONSIGNEE_EXPORTER" type="NUMBER(19, 0)"/>
            <column name="C_SWITCH_DOCUMENT_NO" type="VARCHAR2(255 CHAR)"/>
            <column name="F_CONTACT_SWITCH_NOTIFY_PARTY" type="NUMBER(19, 0)"/>
            <column name="F_SWITCH_PORT_AS_DISCHARGE" type="NUMBER(19, 0)">
                <constraints nullable="false"/>
            </column>
            <column name="F_SWITCH_PORT_AS_LOADING" type="NUMBER(19, 0)">
                <constraints nullable="false"/>
            </column>
            <column name="F_CONTACT_SWITCH_SHIPPER_EXPORTER" type="NUMBER(19, 0)"/>
        </createTable>
    </changeSet>

    <changeSet author="saeb (generated)" id="1596267426191-242">
        <addForeignKeyConstraint baseColumnNames="F_CONTACT_CONSIGNEE_EXPORTER" baseTableName="TBL_CNTR_BILL_OF_LANDING" constraintName="FK_BILL_OF_LANDING_TO_CONTACT_AS_CONSIGNEE" deferrable="false" initiallyDeferred="false" referencedColumnNames="ID" referencedTableName="TBL_CONTACT" validate="true"/>
    </changeSet>
    <changeSet author="saeb (generated)" id="1596267426191-243">
        <addForeignKeyConstraint baseColumnNames="F_CONTACT_SHIPPER_EXPORTER" baseTableName="TBL_CNTR_BILL_OF_LANDING" constraintName="FK_BILL_OF_LANDING_TO_CONTACT_AS_EXPORTER" deferrable="false" initiallyDeferred="false" referencedColumnNames="ID" referencedTableName="TBL_CONTACT" validate="true"/>
    </changeSet>
    <changeSet author="saeb (generated)" id="1596267426191-244">
        <addForeignKeyConstraint baseColumnNames="F_CONTACT_NOTIFY_PARTY" baseTableName="TBL_CNTR_BILL_OF_LANDING" constraintName="FK_BILL_OF_LANDING_TO_CONTACT_AS_NOTIFY_PARTY" deferrable="false" initiallyDeferred="false" referencedColumnNames="ID" referencedTableName="TBL_CONTACT" validate="true"/>
    </changeSet>
    <changeSet author="saeb (generated)" id="1596267426191-245">
        <addForeignKeyConstraint baseColumnNames="F_CONTACT_SWITCH_CONSIGNEE_EXPORTER" baseTableName="TBL_CNTR_BILL_OF_LANDING" constraintName="FK_BILL_OF_LANDING_TO_CONTACT_AS_SWITCH_CONSIGNEE" deferrable="false" initiallyDeferred="false" referencedColumnNames="ID" referencedTableName="TBL_CONTACT" validate="true"/>
    </changeSet>
    <changeSet author="saeb (generated)" id="1596267426191-246">
        <addForeignKeyConstraint baseColumnNames="F_CONTACT_SWITCH_SHIPPER_EXPORTER" baseTableName="TBL_CNTR_BILL_OF_LANDING" constraintName="FK_BILL_OF_LANDING_TO_CONTACT_AS_SWITCH_EXPORTER" deferrable="false" initiallyDeferred="false" referencedColumnNames="ID" referencedTableName="TBL_CONTACT" validate="true"/>
    </changeSet>
    <changeSet author="saeb (generated)" id="1596267426191-247">
        <addForeignKeyConstraint baseColumnNames="F_CONTACT_SWITCH_NOTIFY_PARTY" baseTableName="TBL_CNTR_BILL_OF_LANDING" constraintName="FK_BILL_OF_LANDING_TO_CONTACT_AS_SWITCH_NOTIFY_PARTY" deferrable="false" initiallyDeferred="false" referencedColumnNames="ID" referencedTableName="TBL_CONTACT" validate="true"/>
    </changeSet>
    <changeSet author="saeb (generated)" id="1596267426191-248">
        <addForeignKeyConstraint baseColumnNames="F_PORT_AS_DISCHARGE" baseTableName="TBL_CNTR_BILL_OF_LANDING" constraintName="FK_BILL_OF_LANDING_TO_PORT_AS_DISCHARGE" deferrable="false" initiallyDeferred="false" referencedColumnNames="ID" referencedTableName="TBL_PORT" validate="true"/>
    </changeSet>
    <changeSet author="saeb (generated)" id="1596267426191-249">
        <addForeignKeyConstraint baseColumnNames="F_PORT_AS_LOADING" baseTableName="TBL_CNTR_BILL_OF_LANDING" constraintName="FK_BILL_OF_LANDING_TO_PORT_AS_LOADING" deferrable="false" initiallyDeferred="false" referencedColumnNames="ID" referencedTableName="TBL_PORT" validate="true"/>
    </changeSet>
    <changeSet author="saeb (generated)" id="1596267426191-250">
        <addForeignKeyConstraint baseColumnNames="F_SWITCH_PORT_AS_DISCHARGE" baseTableName="TBL_CNTR_BILL_OF_LANDING" constraintName="FK_BILL_OF_LANDING_TO_SWITCH_PORT_AS_DISCHARGE" deferrable="false" initiallyDeferred="false" referencedColumnNames="ID" referencedTableName="TBL_PORT" validate="true"/>
    </changeSet>
    <changeSet author="saeb (generated)" id="1596267426191-251">
        <addForeignKeyConstraint baseColumnNames="F_SWITCH_PORT_AS_LOADING" baseTableName="TBL_CNTR_BILL_OF_LANDING" constraintName="FK_BILL_OF_LANDING_TO_SWITCH_PORT_AS_LOADING" deferrable="false" initiallyDeferred="false" referencedColumnNames="ID" referencedTableName="TBL_PORT" validate="true"/>
    </changeSet>
    <changeSet author="saeb (generated)" id="1596267426191-252">
        <addForeignKeyConstraint baseColumnNames="F_VESSEL" baseTableName="TBL_CNTR_BILL_OF_LANDING" constraintName="FK_BILL_OF_LANDING_TO_VESSEL" deferrable="false" initiallyDeferred="false" referencedColumnNames="ID" referencedTableName="TBL_VESSEL" validate="true"/>
    </changeSet>
    <changeSet author="saeb (generated)" id="1596441538809-252">
        <addColumn tableName="TBL_CNTR_BILL_OF_LANDING">
            <column name="N_TOTAL_BUNDLES" type="number(10, 0)"/>
        </addColumn>
    </changeSet>
    <changeSet author="saeb (generated)" id="1596441538809-253">
        <addColumn tableName="TBL_CNTR_BILL_OF_LANDING">
            <column name="N_TOTAL_GROSS" type="number(10, 0)"/>
        </addColumn>
    </changeSet>
    <changeSet author="saeb (generated)" id="1596441538809-254">
        <addColumn tableName="TBL_CNTR_BILL_OF_LANDING">
            <column name="N_TOTAL_NET" type="number(10, 0)"/>
        </addColumn>
    </changeSet>
    <changeSet author="saeb (generated)" id="1596441538809-255">
        <addUniqueConstraint columnNames="C_DOCUMENT_NO" constraintName="UC_TBL_CNTR_BILL_OF_LANDINGC_DOCUMENT_NO_COL" tableName="TBL_CNTR_BILL_OF_LANDING"/>
    </changeSet>
</databaseChangeLog>
